{"createdAt":"2025-06-02T14:43:14.727Z","updatedAt":"2025-06-03T21:36:33.758Z","id":"U3k48GddiML0cpuS","name":"13 - ATUALIZA CREDENCIAL DO YOUTUBE","active":false,"isArchived":false,"nodes":[{"parameters":{},"type":"n8n-nodes-base.manualTrigger","typeVersion":1,"position":[0,0],"id":"6464595b-507e-4bc0-acf7-4e519875cc68","name":"When clicking ‘Test workflow’"},{"parameters":{"returnAll":true,"filters":{},"options":{}},"type":"n8n-nodes-base.youTube","typeVersion":1,"position":[220,0],"id":"e1f7565b-56dd-446e-8b02-25f2843fa583","name":"@historiasqueomundoesconde","credentials":{"youTubeOAuth2Api":{"id":"oILeEZ5ajeJ2Mh3K","name":"@historiasqueomundoesconde"}}}],"connections":{"When clicking ‘Test workflow’":{"main":[[{"node":"@historiasqueomundoesconde","type":"main","index":0}]]}},"settings":{"executionOrder":"v1"},"staticData":null,"meta":{"templateCredsSetupCompleted":true},"pinData":{},"versionId":"a6b3fa2c-35e9-48b2-9e83-f0e29096b3df","triggerCount":0,"tags":[{"createdAt":"2025-06-03T13:08:52.656Z","updatedAt":"2025-06-03T13:08:52.656Z","id":"5X46tRV4lwQwBhLN","name":"teste ok"}]}